odoo/addons/ssi_hr_payroll_timesheet/README.rst
odoo/addons/ssi_hr_payroll_timesheet/__init__.py
odoo/addons/ssi_hr_payroll_timesheet/__manifest__.py
odoo/addons/ssi_hr_payroll_timesheet/models/__init__.py
odoo/addons/ssi_hr_payroll_timesheet/models/hr_payslip.py
odoo/addons/ssi_hr_payroll_timesheet/static/description/icon.png
odoo/addons/ssi_hr_payroll_timesheet/views/hr_payslip_views.xml
odoo14_addon_ssi_hr_payroll_timesheet-14.0.1.1.2.dev1.dist-info/METADATA
odoo14_addon_ssi_hr_payroll_timesheet-14.0.1.1.2.dev1.dist-info/WHEEL
odoo14_addon_ssi_hr_payroll_timesheet-14.0.1.1.2.dev1.dist-info/top_level.txt
odoo14_addon_ssi_hr_payroll_timesheet-14.0.1.1.2.dev1.dist-info/RECORD
